{"version": 0.6, "generator": "Overpass API 0.7.61.5 4133829e", "osm3s": {"timestamp_osm_base": "2024-03-21T14:58:46Z", "copyright": "The data included in this document is from www.openstreetmap.org. The data is made available under ODbL."}, "elements": [{"type": "node", "id": 1069060062, "lat": 29.4633689, "lon": -9.940015, "tags": {"power": "tower"}}, {"type": "node", "id": 2476256431, "lat": 29.4217486, "lon": -9.9845533, "tags": {"power": "tower"}}, {"type": "node", "id": 2940674950, "lat": 29.4684385, "lon": -9.9363635, "tags": {"power": "tower"}}, {"type": "node", "id": 2940675413, "lat": 29.5183682, "lon": -9.9161267, "tags": {"power": "tower"}}, {"type": "node", "id": 2940675486, "lat": 29.4951337, "lon": -9.9217612, "tags": {"power": "tower"}}, {"type": "node", "id": 2940675527, "lat": 29.4566215, "lon": -9.9448748, "tags": {"power": "tower"}}, {"type": "node", "id": 2940675539, "lat": 29.4704951, "lon": -9.9348821, "tags": {"power": "tower"}}, {"type": "node", "id": 2940675550, "lat": 29.4453464, "lon": -9.9529949, "tags": {"power": "tower"}}, {"type": "node", "id": 2940675578, "lat": 29.4790611, "lon": -9.9287116, "tags": {"power": "tower"}}, {"type": "node", "id": 2940675724, "lat": 29.4553533, "lon": -9.9457882, "tags": {"power": "tower"}}, {"type": "node", "id": 2940675734, "lat": 29.5046821, "lon": -9.9194458, "tags": {"power": "tower"}}, {"type": "node", "id": 2940675743, "lat": 29.4529844, "lon": -9.9474943, "tags": {"power": "tower"}}, {"type": "node", "id": 2940675810, "lat": 29.500187, "lon": -9.9205359, "tags": {"power": "tower"}}, {"type": "node", "id": 2940675855, "lat": 29.4658951, "lon": -9.9381955, "tags": {"power": "tower"}}, {"type": "node", "id": 2940675867, "lat": 29.521374, "lon": -9.9153976, "tags": {"power": "tower"}}, {"type": "node", "id": 2940676005, "lat": 29.5152045, "lon": -9.916894, "tags": {"power": "tower"}}, {"type": "node", "id": 2940676112, "lat": 29.4812574, "lon": -9.9271294, "tags": {"power": "tower"}}, {"type": "node", "id": 2940676128, "lat": 29.5236845, "lon": -9.9147884, "tags": {"power": "tower"}}, {"type": "node", "id": 2940676146, "lat": 29.4470378, "lon": -9.9517768, "tags": {"power": "tower"}}, {"type": "node", "id": 2940676148, "lat": 29.4771358, "lon": -9.9300985, "tags": {"power": "tower"}}, {"type": "node", "id": 2940676206, "lat": 29.4392826, "lon": -9.9573615, "tags": {"power": "tower"}}, {"type": "node", "id": 2940676265, "lat": 29.4902287, "lon": -9.9229506, "tags": {"power": "tower"}}, {"type": "node", "id": 2940676410, "lat": 29.4610273, "lon": -9.9417016, "tags": {"power": "tower"}}, {"type": "node", "id": 2940676457, "lat": 29.4492671, "lon": -9.9501714, "tags": {"power": "tower"}}, {"type": "node", "id": 2940676469, "lat": 29.4854496, "lon": -9.9241093, "tags": {"power": "tower"}}, {"type": "node", "id": 2940676479, "lat": 29.4976224, "lon": -9.9211578, "tags": {"power": "tower"}}, {"type": "node", "id": 2940676484, "lat": 29.4835046, "lon": -9.9255105, "tags": {"power": "tower"}}, {"type": "node", "id": 2940676485, "lat": 29.4511761, "lon": -9.9487966, "tags": {"power": "tower"}}, {"type": "node", "id": 2940676496, "lat": 29.5109243, "lon": -9.917932, "tags": {"power": "tower"}}, {"type": "node", "id": 2940676545, "lat": 29.4726492, "lon": -9.9333304, "tags": {"power": "tower"}}, {"type": "node", "id": 2940676546, "lat": 29.441409, "lon": -9.9558303, "tags": {"power": "tower"}}, {"type": "node", "id": 2940676565, "lat": 29.5030028, "lon": -9.9198531, "tags": {"power": "tower"}}, {"type": "node", "id": 2940676567, "lat": 29.5128828, "lon": -9.917457, "tags": {"power": "tower"}}, {"type": "node", "id": 2940676580, "lat": 29.4924022, "lon": -9.9224236, "tags": {"power": "tower"}}, {"type": "node", "id": 2940676649, "lat": 29.4751293, "lon": -9.931544, "tags": {"power": "tower"}}, {"type": "node", "id": 2940676691, "lat": 29.4587612, "lon": -9.9433337, "tags": {"power": "tower"}}, {"type": "node", "id": 2940676693, "lat": 29.5081697, "lon": -9.9186001, "tags": {"power": "tower"}}, {"type": "node", "id": 2981617808, "lat": 29.4207096, "lon": -9.9867902, "tags": {"power": "tower"}}, {"type": "node", "id": 2981617809, "lat": 29.4241765, "lon": -9.9793257, "tags": {"power": "tower"}}, {"type": "node", "id": 2981617810, "lat": 29.4069176, "lon": -10.0250203, "tags": {"power": "tower"}}, {"type": "node", "id": 2981617814, "lat": 29.4195091, "lon": -9.9893749, "tags": {"power": "tower"}}, {"type": "node", "id": 2981617822, "lat": 29.4292274, "lon": -9.9684502, "tags": {"power": "tower"}}, {"type": "node", "id": 2981618071, "lat": 29.4099408, "lon": -10.013802, "tags": {"power": "tower"}}, {"type": "node", "id": 2981618080, "lat": 29.433383, "lon": -9.9616097, "tags": {"power": "tower"}}, {"type": "node", "id": 2981618119, "lat": 29.4077651, "lon": -10.0218754, "tags": {"power": "tower"}}, {"type": "node", "id": 2981618120, "lat": 29.4349632, "lon": -9.9604719, "tags": {"power": "tower"}}, {"type": "node", "id": 2981618122, "lat": 29.4123971, "lon": -10.0046868, "tags": {"power": "tower"}}, {"type": "node", "id": 2981618193, "lat": 29.4279176, "lon": -9.9712705, "tags": {"power": "tower"}}, {"type": "node", "id": 2981618195, "lat": 29.4179012, "lon": -9.9928368, "tags": {"power": "tower"}}, {"type": "node", "id": 2981618199, "lat": 29.4113758, "lon": -10.0084769, "tags": {"power": "tower"}}, {"type": "node", "id": 2981618200, "lat": 29.4264856, "lon": -9.9743537, "tags": {"power": "tower"}}, {"type": "node", "id": 2981618201, "lat": 29.4094383, "lon": -10.0156667, "tags": {"power": "tower"}}, {"type": "node", "id": 2981618205, "lat": 29.4153585, "lon": -9.998311, "tags": {"power": "tower"}}, {"type": "node", "id": 2981618207, "lat": 29.4309981, "lon": -9.9646374, "tags": {"power": "tower"}}, {"type": "node", "id": 2981618232, "lat": 29.408742, "lon": -10.0182504, "tags": {"power": "tower"}}, {"type": "node", "id": 2981618247, "lat": 29.4319124, "lon": -9.9626686, "tags": {"power": "tower"}}, {"type": "node", "id": 2981618351, "lat": 29.4301596, "lon": -9.9664429, "tags": {"power": "tower"}}, {"type": "node", "id": 2981618619, "lat": 29.4229508, "lon": -9.9819647, "tags": {"power": "tower"}}, {"type": "node", "id": 2981618658, "lat": 29.4137693, "lon": -10.0017325, "tags": {"power": "tower"}}, {"type": "node", "id": 2981618781, "lat": 29.4106971, "lon": -10.0109953, "tags": {"power": "tower"}}, {"type": "node", "id": 2981618949, "lat": 29.4256157, "lon": -9.9762269, "tags": {"power": "tower"}}, {"type": "node", "id": 2981619001, "lat": 29.4169137, "lon": -9.9949628, "tags": {"power": "tower"}}, {"type": "node", "id": 3150369298, "lat": 29.4017918, "lon": -10.0438691, "tags": {"power": "tower"}}, {"type": "node", "id": 3150369305, "lat": 29.3979826, "lon": -10.0491531, "tags": {"power": "tower"}}, {"type": "node", "id": 3150369306, "lat": 29.3962113, "lon": -10.0516261, "tags": {"power": "tower"}}, {"type": "node", "id": 3150369308, "lat": 29.4028898, "lon": -10.0397125, "tags": {"power": "tower"}}, {"type": "node", "id": 3150369309, "lat": 29.3997214, "lon": -10.0467981, "tags": {"power": "tower"}}, {"type": "node", "id": 3150369312, "lat": 29.3955196, "lon": -10.0525487, "tags": {"power": "tower"}}, {"type": "node", "id": 3150369314, "lat": 29.4064556, "lon": -10.0264889, "tags": {"power": "tower"}}, {"type": "node", "id": 3150369319, "lat": 29.404848, "lon": -10.0323257, "tags": {"power": "tower"}}, {"type": "node", "id": 5938663277, "lat": 29.4207602, "lon": -10.0954135}, {"type": "node", "id": 5938663278, "lat": 29.420791, "lon": -10.0964385}, {"type": "node", "id": 5938663279, "lat": 29.4208256, "lon": -10.0983957}, {"type": "node", "id": 5938663280, "lat": 29.4208641, "lon": -10.099487}, {"type": "node", "id": 5938663281, "lat": 29.4209295, "lon": -10.1010819}, {"type": "node", "id": 5938663282, "lat": 29.4201518, "lon": -10.101193}, {"type": "node", "id": 5938664443, "lat": 29.4207153, "lon": -10.0934968}, {"type": "node", "id": 5938664444, "lat": 29.4206744, "lon": -10.0924585}, {"type": "node", "id": 5938667390, "lat": 29.4212289, "lon": -10.1011408}, {"type": "node", "id": 5938667391, "lat": 29.422047, "lon": -10.1014591}, {"type": "node", "id": 5938667392, "lat": 29.4231559, "lon": -10.101793}, {"type": "node", "id": 5938667393, "lat": 29.4242284, "lon": -10.1021008}, {"type": "node", "id": 5938667394, "lat": 29.4253146, "lon": -10.1024609}, {"type": "node", "id": 5938667395, "lat": 29.4262962, "lon": -10.1032174}, {"type": "node", "id": 5938667396, "lat": 29.427287, "lon": -10.103974}, {"type": "node", "id": 5938667397, "lat": 29.4282731, "lon": -10.1047306}, {"type": "node", "id": 5938667398, "lat": 29.4286276, "lon": -10.1038853}, {"type": "node", "id": 5938667399, "lat": 29.4291593, "lon": -10.1026852}, {"type": "node", "id": 5938667400, "lat": 29.4296819, "lon": -10.1015426}, {"type": "node", "id": 5938667401, "lat": 29.4300636, "lon": -10.1002173}, {"type": "node", "id": 5938667402, "lat": 29.4301136, "lon": -10.0997685}, {"type": "node", "id": 5938667403, "lat": 29.4305044, "lon": -10.0996694}, {"type": "node", "id": 5938667404, "lat": 29.4306226, "lon": -10.0995546}, {"type": "node", "id": 5938668062, "lat": 29.4305226, "lon": -10.0984693}, {"type": "node", "id": 5938668063, "lat": 29.4312088, "lon": -10.0972797}, {"type": "node", "id": 5938668064, "lat": 29.4318223, "lon": -10.09609}, {"type": "node", "id": 5938668065, "lat": 29.4324903, "lon": -10.0949213}, {"type": "node", "id": 5938673896, "lat": 29.4350578, "lon": -10.0903714}, {"type": "node", "id": 5938673897, "lat": 29.4357031, "lon": -10.0894583}, {"type": "node", "id": 5938673898, "lat": 29.4370436, "lon": -10.0875747}, {"type": "node", "id": 5938673899, "lat": 29.4377116, "lon": -10.0866459}, {"type": "node", "id": 5938673900, "lat": 29.4384795, "lon": -10.0859311}, {"type": "node", "id": 5938673901, "lat": 29.4393247, "lon": -10.0851798}, {"type": "node", "id": 5938673902, "lat": 29.4405925, "lon": -10.084371}, {"type": "node", "id": 5938673903, "lat": 29.4419193, "lon": -10.0840475}, {"type": "node", "id": 5938673904, "lat": 29.4422556, "lon": -10.0836823}, {"type": "node", "id": 5938673905, "lat": 29.44251, "lon": -10.0829727}, {"type": "node", "id": 5938676185, "lat": 29.4430715, "lon": -10.0828627}, {"type": "node", "id": 6611209679, "lat": 29.3736677, "lon": -10.1528896, "tags": {"power": "tower"}}, {"type": "node", "id": 6611209680, "lat": 29.363523, "lon": -10.1231815, "tags": {"power": "tower"}}, {"type": "node", "id": 6611209681, "lat": 29.3643879, "lon": -10.1215132, "tags": {"power": "tower"}}, {"type": "node", "id": 6611209684, "lat": 29.3756732, "lon": -10.1001306, "tags": {"power": "tower"}}, {"type": "node", "id": 6611259085, "lat": 29.3544667, "lon": -10.1411845, "tags": {"power": "tower"}}, {"type": "node", "id": 6611259086, "lat": 29.3723214, "lon": -10.1064016, "tags": {"power": "tower"}}, {"type": "node", "id": 6611259088, "lat": 29.353792, "lon": -10.1633773, "tags": {"power": "tower"}}, {"type": "node", "id": 6611259089, "lat": 29.3554976, "lon": -10.1680133, "tags": {"power": "tower"}}, {"type": "node", "id": 6611259094, "lat": 29.3537279, "lon": -10.1609094, "tags": {"power": "tower"}}, {"type": "node", "id": 6611259095, "lat": 29.3543685, "lon": -10.1642354, "tags": {"power": "tower"}}, {"type": "node", "id": 6611259096, "lat": 29.3840919, "lon": -10.0810762, "tags": {"power": "tower"}}, {"type": "node", "id": 6611259103, "lat": 29.3858074, "lon": -10.0731261, "tags": {"power": "tower"}}, {"type": "node", "id": 6611259108, "lat": 29.3606243, "lon": -10.1287229, "tags": {"power": "tower"}}, {"type": "node", "id": 6611259109, "lat": 29.3596007, "lon": -10.1783876, "tags": {"power": "tower"}}, {"type": "node", "id": 6611259111, "lat": 29.3835357, "lon": -10.0841553, "tags": {"power": "tower"}}, {"type": "node", "id": 6611259113, "lat": 29.3812406, "lon": -10.0897022, "tags": {"power": "tower"}}, {"type": "node", "id": 6611259118, "lat": 29.3739248, "lon": -10.1034458, "tags": {"power": "tower"}}, {"type": "node", "id": 6611259119, "lat": 29.3703673, "lon": -10.1103444, "tags": {"power": "tower"}}, {"type": "node", "id": 6611259120, "lat": 29.3526992, "lon": -10.1577713, "tags": {"power": "tower"}}, {"type": "node", "id": 6611259124, "lat": 29.37809, "lon": -10.0955065, "tags": {"power": "tower"}}, {"type": "node", "id": 6611259126, "lat": 29.3759677, "lon": -10.1536192, "tags": {"power": "tower"}}, {"type": "node", "id": 6611259127, "lat": 29.3681046, "lon": -10.1143785, "tags": {"power": "tower"}}, {"type": "node", "id": 6611259128, "lat": 29.3791557, "lon": -10.0934412, "tags": {"power": "tower"}}, {"type": "node", "id": 6611259129, "lat": 29.3830308, "lon": -10.0861187, "tags": {"power": "tower"}}, {"type": "node", "id": 6611259134, "lat": 29.3617136, "lon": -10.1489575, "tags": {"power": "tower"}}, {"type": "node", "id": 6611259135, "lat": 29.3521756, "lon": -10.1459266, "tags": {"power": "tower"}}, {"type": "node", "id": 6611259136, "lat": 29.352241, "lon": -10.1558615, "tags": {"power": "tower"}}, {"type": "node", "id": 6611259137, "lat": 29.3580174, "lon": -10.1550594, "tags": {"power": "tower"}}, {"type": "node", "id": 6611259138, "lat": 29.3610825, "lon": -10.1277359, "tags": {"power": "tower"}}, {"type": "node", "id": 6611259139, "lat": 29.3513199, "lon": -10.1510014, "tags": {"power": "tower"}}, {"type": "node", "id": 6611259140, "lat": 29.3719567, "lon": -10.1523639, "tags": {"power": "tower"}}, {"type": "node", "id": 6611259143, "lat": 29.3765473, "lon": -10.0984891, "tags": {"power": "tower"}}, {"type": "node", "id": 6611259144, "lat": 29.3508476, "lon": -10.1485981, "tags": {"power": "tower"}}, {"type": "node", "id": 6611259146, "lat": 29.3547519, "lon": -10.1587261, "tags": {"power": "tower"}}, {"type": "node", "id": 6611259147, "lat": 29.3566358, "lon": -10.1714178, "tags": {"power": "tower"}}, {"type": "node", "id": 6611259148, "lat": 29.3660896, "lon": -10.1181979, "tags": {"power": "tower"}}, {"type": "node", "id": 6611259149, "lat": 29.3569428, "lon": -10.1722842, "tags": {"power": "tower"}}, {"type": "node", "id": 6611259150, "lat": 29.3567483, "lon": -10.1570095, "tags": {"power": "tower"}}, {"type": "node", "id": 6611259151, "lat": 29.3561639, "lon": -10.1576425, "tags": {"power": "tower"}}, {"type": "node", "id": 6611259152, "lat": 29.3540926, "lon": -10.1633556, "tags": {"power": "tower"}}, {"type": "node", "id": 6611259153, "lat": 29.3594508, "lon": -10.1522942, "tags": {"power": "tower"}}, {"type": "node", "id": 6611259154, "lat": 29.3674127, "lon": -10.1158912, "tags": {"power": "tower"}}, {"type": "node", "id": 6611259155, "lat": 29.3772485, "lon": -10.1540376, "tags": {"power": "tower"}}, {"type": "node", "id": 6611259159, "lat": 29.3619474, "lon": -10.1260997, "tags": {"power": "tower"}}, {"type": "node", "id": 6611259160, "lat": 29.3573234, "lon": -10.1353855, "tags": {"power": "tower"}}, {"type": "node", "id": 6611259161, "lat": 29.3655333, "lon": -10.1502021, "tags": {"power": "tower"}}, {"type": "node", "id": 6611259164, "lat": 29.3529938, "lon": -10.1593699, "tags": {"power": "tower"}}, {"type": "node", "id": 6611259165, "lat": 29.3877565, "lon": -10.0634433, "tags": {"power": "tower"}}, {"type": "node", "id": 6611259166, "lat": 29.38742, "lon": -10.0651009, "tags": {"power": "tower"}}, {"type": "node", "id": 6611259168, "lat": 29.3553129, "lon": -10.1394679, "tags": {"power": "tower"}}, {"type": "node", "id": 6611259169, "lat": 29.3587604, "lon": -10.1765167, "tags": {"power": "tower"}}, {"type": "node", "id": 6611259170, "lat": 29.3920285, "lon": -10.0574996, "tags": {"power": "tower"}}, {"type": "node", "id": 6611259172, "lat": 29.3932204, "lon": -10.0558473, "tags": {"power": "tower"}}, {"type": "node", "id": 6611259173, "lat": 29.3586419, "lon": -10.153823, "tags": {"power": "tower"}}, {"type": "node", "id": 6611259174, "lat": 29.3588383, "lon": -10.1323654, "tags": {"power": "tower"}}, {"type": "node", "id": 6611259175, "lat": 29.3845547, "lon": -10.0790001, "tags": {"power": "tower"}}, {"type": "node", "id": 6611259182, "lat": 29.3713584, "lon": -10.1083274, "tags": {"power": "tower"}}, {"type": "node", "id": 6611259183, "lat": 29.3608581, "lon": -10.1494618, "tags": {"power": "tower"}}, {"type": "node", "id": 6611259184, "lat": 29.3611573, "lon": -10.1488019, "tags": {"power": "tower"}}, {"type": "node", "id": 6611259185, "lat": 29.3535214, "lon": -10.1597404, "tags": {"power": "tower"}}, {"type": "node", "id": 6611259187, "lat": 29.3530733, "lon": -10.1441081, "tags": {"power": "tower"}}, {"type": "node", "id": 6665108938, "lat": 29.4003911, "lon": -10.1493982}, {"type": "node", "id": 6665108939, "lat": 29.4002284, "lon": -10.1491693}, {"type": "node", "id": 6665108940, "lat": 29.400029, "lon": -10.1489265}, {"type": "node", "id": 6665108941, "lat": 29.3997239, "lon": -10.1484735}, {"type": "node", "id": 6665108942, "lat": 29.3993618, "lon": -10.1480018}, {"type": "node", "id": 6665108943, "lat": 29.3990322, "lon": -10.1475629}, {"type": "node", "id": 6665108944, "lat": 29.3986904, "lon": -10.1470678}, {"type": "node", "id": 6665108945, "lat": 29.3990059, "lon": -10.1464619}, {"type": "node", "id": 6665108946, "lat": 29.3993574, "lon": -10.1458107}, {"type": "node", "id": 6665108947, "lat": 29.3996925, "lon": -10.1451674}, {"type": "node", "id": 6665108948, "lat": 29.4000415, "lon": -10.1445445}, {"type": "node", "id": 6665108949, "lat": 29.4003827, "lon": -10.1439599}, {"type": "node", "id": 6665108950, "lat": 29.4006652, "lon": -10.1434187}, {"type": "node", "id": 6665108951, "lat": 29.4009658, "lon": -10.1428549}, {"type": "node", "id": 6665108952, "lat": 29.4014589, "lon": -10.1425401}, {"type": "node", "id": 6665108953, "lat": 29.4030961, "lon": -10.1415474}, {"type": "node", "id": 6665108954, "lat": 29.4041166, "lon": -10.1410178}, {"type": "node", "id": 6665108955, "lat": 29.4051341, "lon": -10.1405058}, {"type": "node", "id": 6665108956, "lat": 29.4061602, "lon": -10.1399878}, {"type": "node", "id": 6665108957, "lat": 29.4072209, "lon": -10.1394392}, {"type": "node", "id": 6665108958, "lat": 29.4082349, "lon": -10.1389192}, {"type": "node", "id": 6665108959, "lat": 29.4092548, "lon": -10.1383834}, {"type": "node", "id": 6665108960, "lat": 29.4103199, "lon": -10.1378408}, {"type": "node", "id": 6665108961, "lat": 29.4114453, "lon": -10.1372791}, {"type": "node", "id": 6665108962, "lat": 29.4128517, "lon": -10.1365916}, {"type": "node", "id": 6665108963, "lat": 29.4141108, "lon": -10.1359542}, {"type": "node", "id": 6665108964, "lat": 29.4157782, "lon": -10.1351027}, {"type": "node", "id": 6665108965, "lat": 29.4170946, "lon": -10.1344476}, {"type": "node", "id": 6665108966, "lat": 29.4185423, "lon": -10.133728}, {"type": "node", "id": 6665108967, "lat": 29.4194041, "lon": -10.1333057}, {"type": "node", "id": 6665108968, "lat": 29.4196376, "lon": -10.1331917}, {"type": "node", "id": 6665108969, "lat": 29.4205915, "lon": -10.1326959}, {"type": "node", "id": 6665108970, "lat": 29.4220624, "lon": -10.131973}, {"type": "node", "id": 6665108971, "lat": 29.4230052, "lon": -10.1314887}, {"type": "node", "id": 6665108972, "lat": 29.4239499, "lon": -10.1310131}, {"type": "node", "id": 6665108973, "lat": 29.4251133, "lon": -10.1304306}, {"type": "node", "id": 6665108974, "lat": 29.4253925, "lon": -10.1300004}, {"type": "node", "id": 6665108975, "lat": 29.4262816, "lon": -10.1287}, {"type": "node", "id": 6665108976, "lat": 29.4275357, "lon": -10.1267131}, {"type": "node", "id": 6665108977, "lat": 29.4279733, "lon": -10.1260879}, {"type": "node", "id": 6665108978, "lat": 29.4288849, "lon": -10.1245568}, {"type": "node", "id": 6665108979, "lat": 29.42922, "lon": -10.1238232}, {"type": "node", "id": 6665108980, "lat": 29.4301815, "lon": -10.1217359}, {"type": "node", "id": 6665108981, "lat": 29.4306404, "lon": -10.1208331}, {"type": "node", "id": 6665108982, "lat": 29.4310959, "lon": -10.1199448}, {"type": "node", "id": 6665108983, "lat": 29.4323545, "lon": -10.1175542}, {"type": "node", "id": 6665108984, "lat": 29.4329228, "lon": -10.1164712}, {"type": "node", "id": 6665108985, "lat": 29.4334718, "lon": -10.1154134}, {"type": "node", "id": 6665108986, "lat": 29.4336508, "lon": -10.1150585}, {"type": "node", "id": 6665108987, "lat": 29.432948, "lon": -10.1148777}, {"type": "node", "id": 6665108988, "lat": 29.4327816, "lon": -10.1147111}, {"type": "node", "id": 6665108989, "lat": 29.4322575, "lon": -10.1141744}, {"type": "node", "id": 6665108990, "lat": 29.432246, "lon": -10.1128432}, {"type": "node", "id": 6665108991, "lat": 29.432817, "lon": -10.1147466}, {"type": "node", "id": 6665108992, "lat": 29.433037, "lon": -10.1145195}, {"type": "node", "id": 6665108993, "lat": 29.4336971, "lon": -10.1139588}, {"type": "node", "id": 6665108994, "lat": 29.434368, "lon": -10.1131146}, {"type": "node", "id": 6665108995, "lat": 29.4363518, "lon": -10.1109043}, {"type": "node", "id": 6665108996, "lat": 29.4381463, "lon": -10.1100666}, {"type": "node", "id": 6665108997, "lat": 29.438661, "lon": -10.1098301}, {"type": "node", "id": 6665108998, "lat": 29.4394592, "lon": -10.1095175}, {"type": "node", "id": 6665108999, "lat": 29.4405664, "lon": -10.1093673}, {"type": "node", "id": 6665109000, "lat": 29.4412963, "lon": -10.1091983}, {"type": "node", "id": 6665109001, "lat": 29.4424546, "lon": -10.1085544}, {"type": "node", "id": 6665109002, "lat": 29.4432133, "lon": -10.1081657}, {"type": "node", "id": 6665109003, "lat": 29.4440168, "lon": -10.1076749}, {"type": "node", "id": 6665109004, "lat": 29.4445534, "lon": -10.1070402}, {"type": "node", "id": 6665109005, "lat": 29.4442824, "lon": -10.1068677}, {"type": "node", "id": 6665109006, "lat": 29.4439685, "lon": -10.1066274}, {"type": "node", "id": 6665109007, "lat": 29.4436895, "lon": -10.1064117}, {"type": "node", "id": 6665109008, "lat": 29.443397, "lon": -10.1061806}, {"type": "node", "id": 6665109024, "lat": 29.5276921, "lon": -9.9138296, "tags": {"power": "tower"}}, {"type": "node", "id": 6665109025, "lat": 29.5292133, "lon": -9.9134384, "tags": {"power": "tower"}}, {"type": "node", "id": 6665109026, "lat": 29.5339075, "lon": -9.912314, "tags": {"power": "tower"}}, {"type": "node", "id": 6665109032, "lat": 29.5988344, "lon": -9.9214766}, {"type": "node", "id": 6665109033, "lat": 29.598993, "lon": -9.9209777, "tags": {"power": "tower"}}, {"type": "node", "id": 6665109034, "lat": 29.5978873, "lon": -9.9197581, "tags": {"power": "tower"}}, {"type": "node", "id": 6665109049, "lat": 29.5960558, "lon": -9.9191958, "tags": {"power": "tower"}}, {"type": "node", "id": 6665109050, "lat": 29.5938941, "lon": -9.9185381, "tags": {"power": "tower"}}, {"type": "node", "id": 6665109051, "lat": 29.5918893, "lon": -9.9179337, "tags": {"power": "tower"}}, {"type": "node", "id": 6665109052, "lat": 29.5898269, "lon": -9.91732, "tags": {"power": "tower"}}, {"type": "node", "id": 6665109053, "lat": 29.5879771, "lon": -9.9167537, "tags": {"power": "tower"}}, {"type": "node", "id": 6665109054, "lat": 29.5859757, "lon": -9.9161448, "tags": {"power": "tower"}}, {"type": "node", "id": 6665109055, "lat": 29.5842097, "lon": -9.9156105, "tags": {"power": "tower"}}, {"type": "node", "id": 6665109056, "lat": 29.5818844, "lon": -9.9149034, "tags": {"power": "tower"}}, {"type": "node", "id": 6665109057, "lat": 29.58005, "lon": -9.9143506, "tags": {"power": "tower"}}, {"type": "node", "id": 6665109058, "lat": 29.5783238, "lon": -9.9146666, "tags": {"power": "tower"}}, {"type": "node", "id": 6665109059, "lat": 29.5765661, "lon": -9.9149861, "tags": {"power": "tower"}}, {"type": "node", "id": 6665109060, "lat": 29.5748189, "lon": -9.9152927, "tags": {"power": "tower"}}, {"type": "node", "id": 6665109061, "lat": 29.5730763, "lon": -9.915619, "tags": {"power": "tower"}}, {"type": "node", "id": 6665109062, "lat": 29.5710448, "lon": -9.9159904, "tags": {"power": "tower"}}, {"type": "node", "id": 6665109063, "lat": 29.5691153, "lon": -9.9163381, "tags": {"power": "tower"}}, {"type": "node", "id": 6665109064, "lat": 29.5668868, "lon": -9.916756, "tags": {"power": "tower"}}, {"type": "node", "id": 6665109065, "lat": 29.5649715, "lon": -9.9171044, "tags": {"power": "tower"}}, {"type": "node", "id": 6665109066, "lat": 29.5626903, "lon": -9.9175215, "tags": {"power": "tower"}}, {"type": "node", "id": 6665109067, "lat": 29.5604389, "lon": -9.9179332, "tags": {"power": "tower"}}, {"type": "node", "id": 6665109068, "lat": 29.5571299, "lon": -9.916323, "tags": {"power": "tower"}}, {"type": "node", "id": 6665109070, "lat": 29.3592825, "lon": -10.1797342, "tags": {"power": "tower"}}, {"type": "node", "id": 6665109071, "lat": 29.3592073, "lon": -10.1800526}, {"type": "node", "id": 6670530386, "lat": 29.3597307, "lon": -10.1784237, "tags": {"power": "tower"}}, {"type": "node", "id": 6670530387, "lat": 29.35898, "lon": -10.1766817, "tags": {"power": "tower"}}, {"type": "node", "id": 6670530388, "lat": 29.3582554, "lon": -10.1750965, "tags": {"power": "tower"}}, {"type": "node", "id": 6670530389, "lat": 29.3577708, "lon": -10.1740598, "tags": {"power": "tower"}}, {"type": "node", "id": 6670530390, "lat": 29.3568942, "lon": -10.1715399, "tags": {"power": "tower"}}, {"type": "node", "id": 6670530391, "lat": 29.3557563, "lon": -10.1680377, "tags": {"power": "tower"}}, {"type": "node", "id": 6670530394, "lat": 29.3984277, "lon": -10.1475176}, {"type": "node", "id": 6670530395, "lat": 29.3980814, "lon": -10.1481739}, {"type": "node", "id": 6670530396, "lat": 29.3973795, "lon": -10.1494303}, {"type": "node", "id": 6670530397, "lat": 29.3966996, "lon": -10.1506866}, {"type": "node", "id": 6670530398, "lat": 29.3959985, "lon": -10.151958}, {"type": "node", "id": 6670530399, "lat": 29.3949665, "lon": -10.1538553}, {"type": "node", "id": 6670530400, "lat": 29.3946342, "lon": -10.1544898}, {"type": "node", "id": 6670530401, "lat": 29.3939516, "lon": -10.1557647}, {"type": "node", "id": 6670530402, "lat": 29.3798786, "lon": -10.1642633}, {"type": "node", "id": 6670530403, "lat": 29.3803511, "lon": -10.1633482}, {"type": "node", "id": 6670530404, "lat": 29.3804702, "lon": -10.1624794}, {"type": "node", "id": 6670530405, "lat": 29.3806366, "lon": -10.1612131}, {"type": "node", "id": 6670530406, "lat": 29.3816608, "lon": -10.1604687}, {"type": "node", "id": 6670530407, "lat": 29.3830388, "lon": -10.1595052}, {"type": "node", "id": 6670530408, "lat": 29.3840839, "lon": -10.1588384}, {"type": "node", "id": 6670530409, "lat": 29.385643, "lon": -10.1575781}, {"type": "node", "id": 6670530410, "lat": 29.3861348, "lon": -10.1572106}, {"type": "node", "id": 6670530411, "lat": 29.3861226, "lon": -10.1571546}, {"type": "node", "id": 6670530412, "lat": 29.3860575, "lon": -10.1572013}, {"type": "node", "id": 6670530413, "lat": 29.3858459, "lon": -10.1568277}, {"type": "node", "id": 6670530414, "lat": 29.3905764, "lon": -10.076483}, {"type": "node", "id": 6670530415, "lat": 29.3906008, "lon": -10.076936}, {"type": "node", "id": 6670530416, "lat": 29.3906497, "lon": -10.0780428}, {"type": "node", "id": 6670530417, "lat": 29.3907272, "lon": -10.0794242}, {"type": "node", "id": 6670530418, "lat": 29.3908105, "lon": -10.0808089}, {"type": "node", "id": 6670530419, "lat": 29.3909017, "lon": -10.0821926}, {"type": "node", "id": 6670530420, "lat": 29.3909823, "lon": -10.0835886}, {"type": "node", "id": 6670530421, "lat": 29.3910628, "lon": -10.0849736}, {"type": "node", "id": 6670530422, "lat": 29.3911433, "lon": -10.0863692}, {"type": "node", "id": 6670530423, "lat": 29.3912212, "lon": -10.0876293}, {"type": "node", "id": 6670530424, "lat": 29.391291, "lon": -10.0888617}, {"type": "node", "id": 6670530425, "lat": 29.3913581, "lon": -10.0900973}, {"type": "node", "id": 6670530426, "lat": 29.3912937, "lon": -10.0913483}, {"type": "node", "id": 6670530427, "lat": 29.3912319, "lon": -10.0925654}, {"type": "node", "id": 6670530428, "lat": 29.3911675, "lon": -10.0937851}, {"type": "node", "id": 6670530429, "lat": 29.3910977, "lon": -10.094845}, {"type": "node", "id": 6670530430, "lat": 29.3918794, "lon": -10.0954947}, {"type": "node", "id": 6670530431, "lat": 29.3919596, "lon": -10.0959335}, {"type": "node", "id": 6670530432, "lat": 29.3916265, "lon": -10.0966308}, {"type": "node", "id": 6670530433, "lat": 29.3913583, "lon": -10.0976961}, {"type": "node", "id": 6670530434, "lat": 29.3913795, "lon": -10.0989463}, {"type": "node", "id": 6670530435, "lat": 29.3913949, "lon": -10.1001178}, {"type": "node", "id": 6670530436, "lat": 29.3918051, "lon": -10.100808}, {"type": "node", "id": 6670530437, "lat": 29.3934795, "lon": -10.1035969}, {"type": "node", "id": 6670530438, "lat": 29.3931742, "lon": -10.1049099}, {"type": "node", "id": 6670530439, "lat": 29.3928967, "lon": -10.1061982}, {"type": "node", "id": 6670530440, "lat": 29.3926161, "lon": -10.1068494}, {"type": "node", "id": 6670530441, "lat": 29.3915553, "lon": -10.1092419}, {"type": "node", "id": 6670530442, "lat": 29.3912932, "lon": -10.1098648}, {"type": "node", "id": 8198958638, "lat": 29.3592996, "lon": -10.1800749}, {"type": "node", "id": 8198958640, "lat": 29.3576341, "lon": -10.1741323, "tags": {"power": "tower"}}, {"type": "node", "id": 8198958641, "lat": 29.3593803, "lon": -10.1797609, "tags": {"power": "tower"}}, {"type": "node", "id": 8198958647, "lat": 29.3581974, "lon": -10.1753655, "tags": {"power": "tower"}}, {"type": "node", "id": 10609298594, "lat": 29.3794321, "lon": -10.1547709, "tags": {"power": "tower"}}, {"type": "node", "id": 10609298595, "lat": 29.38111, "lon": -10.1553151, "tags": {"power": "tower"}}, {"type": "node", "id": 10609298596, "lat": 29.3832582, "lon": -10.1560515, "tags": {"power": "tower"}}, {"type": "node", "id": 10609298597, "lat": 29.3839916, "lon": -10.156294, "tags": {"power": "tower"}}, {"type": "node", "id": 10609298598, "lat": 29.3853705, "lon": -10.1567331, "tags": {"power": "tower"}}, {"type": "node", "id": 11189776186, "lat": 29.5536195, "lon": -9.9128638, "tags": {"power": "tower"}}, {"type": "node", "id": 11189776187, "lat": 29.5504052, "lon": -9.9111351, "tags": {"power": "tower"}}, {"type": "node", "id": 11189776188, "lat": 29.5477663, "lon": -9.9104178, "tags": {"power": "tower"}}, {"type": "node", "id": 11189776189, "lat": 29.5417344, "lon": -9.9103895, "tags": {"power": "tower"}}, {"type": "node", "id": 11189776190, "lat": 29.5385386, "lon": -9.9112129, "tags": {"power": "tower"}}, {"type": "node", "id": 11189776191, "lat": 29.537415, "lon": -9.9114704, "tags": {"power": "tower"}}, {"type": "node", "id": 11189786400, "lat": 29.3571793, "lon": -10.1723662, "tags": {"power": "tower"}}, {"type": "way", "id": 290550316, "nodes": [6665109032, 6665109033, 6665109034, 6665109049, 6665109050, 6665109051, 6665109052, 6665109053, 6665109054, 6665109055, 6665109056, 6665109057, 6665109058, 6665109059, 6665109060, 6665109061, 6665109062, 6665109063, 6665109064, 6665109065, 6665109066, 6665109067, 6665109068, 11189776186, 11189776187, 11189776188, 11189776189, 11189776190, 11189776191, 6665109026, 6665109025, 6665109024, 2940676128, 2940675867, 2940675413, 2940676005, 2940676567, 2940676496, 2940676693, 2940675734, 2940676565, 2940675810, 2940676479, 2940675486, 2940676580, 2940676265, 2940676469, 2940676484, 2940676112, 2940675578, 2940676148, 2940676649, 2940676545, 2940675539, 2940674950, 2940675855, 1069060062, 2940676410, 2940676691, 2940675527, 2940675724, 2940675743, 2940676485, 2940676457, 2940676146, 2940675550, 2940676546, 2940676206, 2981618120, 2981618080, 2981618247, 2981618207, 2981618351, 2981617822, 2981618193, 2981618200, 2981618949, 2981617809, 2981618619, 2476256431, 2981617808, 2981617814, 2981618195, 2981619001, 2981618205, 2981618658, 2981618122, 2981618199, 2981618781, 2981618071, 2981618201, 2981618232, 2981618119, 2981617810, 3150369314, 3150369319, 3150369308, 3150369298, 3150369309, 3150369305, 3150369306, 3150369312, 6611259172, 6611259170, 6611259165, 6611259166, 6611259103, 6611259175, 6611259096, 6611259111, 6611259129, 6611259113, 6611259128, 6611259124, 6611259143, 6611209684, 6611259118, 6611259086, 6611259182, 6611259119, 6611259127, 6611259154, 6611259148, 6611209681, 6611209680, 6611259159, 6611259138, 6611259108, 6611259174, 6611259160, 6611259168, 6611259085, 6611259187, 6611259135, 6611259144, 6611259139, 6611259136, 6611259120, 6611259164, 6611259088, 6611259089, 6611259147, 6611259149, 8198958640, 8198958647, 6611259169, 6611259109, 6665109070, 6665109071], "tags": {"power": "line", "voltage": "60000"}}, {"type": "way", "id": 629001710, "nodes": [5938664444, 5938664443, 5938663277, 5938663278, 5938663279, 5938663280, 5938663281, 5938663282, 5938667390, 5938667391, 5938667392, 5938667393, 5938667394, 5938667395, 5938667396, 5938667397, 5938667398, 5938667399, 5938667400, 5938667401, 5938667402, 5938667403, 5938667404, 5938668062, 5938668063, 5938668064, 5938668065, 5938673896, 5938673897, 5938673898, 5938673899, 5938673900, 5938673901, 5938673902, 5938673903, 5938673904, 5938673905, 5938676185], "tags": {"operator": "ligne 22 KV", "power": "line", "voltage": "22000"}}, {"type": "way", "id": 709167390, "nodes": [6665108938, 6665108939, 6665108940, 6665108941, 6665108942, 6665108943, 6665108944], "tags": {"power": "minor_line"}}, {"type": "way", "id": 709167391, "nodes": [6665108944, 6665108945, 6665108946, 6665108947, 6665108948, 6665108949, 6665108950, 6665108951, 6665108952, 6665108953, 6665108954, 6665108955, 6665108956, 6665108957, 6665108958, 6665108959, 6665108960, 6665108961, 6665108962], "tags": {"power": "minor_line", "voltage": "22000"}}, {"type": "way", "id": 709167392, "nodes": [6665108962, 6665108963, 6665108964, 6665108965, 6665108966, 6665108967, 6665108968, 6665108969, 6665108970, 6665108971, 6665108972, 6665108973, 6665108974, 6665108975, 6665108976, 6665108977, 6665108978, 6665108979, 6665108980, 6665108981, 6665108982, 6665108983, 6665108984, 6665108985, 6665108986], "tags": {"power": "minor_line"}}, {"type": "way", "id": 709167393, "nodes": [6665108985, 6665108987, 6665108991, 6665108988, 6665108989, 6665108990], "tags": {"power": "minor_line", "voltage": "22000"}}, {"type": "way", "id": 709167394, "nodes": [6665108991, 6665108992, 6665108993, 6665108994, 6665108995, 6665108996, 6665108997, 6665108998, 6665108999, 6665109000, 6665109001, 6665109002, 6665109003, 6665109004, 6665109005, 6665109006, 6665109007, 6665109008], "tags": {"power": "minor_line", "voltage": "22000"}}, {"type": "way", "id": 709686127, "nodes": [8198958638, 8198958641, 6670530386, 6670530387, 6670530388, 6670530389, 11189786400, 6670530390, 6670530391, 6611259095, 6611259152, 6611259094, 6611259185, 6611259146, 6611259151, 6611259150, 6611259137, 6611259173, 6611259153, 6611259183, 6611259184, 6611259134, 6611259161, 6611259140, 6611209679, 6611259126, 6611259155, 10609298594, 10609298595, 10609298596, 10609298597, 10609298598], "tags": {"power": "line"}}, {"type": "way", "id": 709686128, "nodes": [6670530401, 6670530400, 6670530399, 6670530398, 6670530397, 6670530396, 6670530395, 6670530394, 6665108944], "tags": {"power": "minor_line", "voltage": "22000"}}, {"type": "way", "id": 709686129, "nodes": [6670530402, 6670530403, 6670530404, 6670530405, 6670530406, 6670530407, 6670530408, 6670530409, 6670530410, 6670530411, 6670530412, 6670530413], "tags": {"power": "minor_line", "voltage": "22000"}}, {"type": "way", "id": 709686130, "nodes": [6670530414, 6670530415, 6670530416, 6670530417, 6670530418, 6670530419, 6670530420, 6670530421, 6670530422, 6670530423, 6670530424, 6670530425, 6670530426, 6670530427, 6670530428, 6670530429, 6670530430, 6670530431, 6670530432, 6670530433, 6670530434, 6670530435, 6670530436, 6670530437, 6670530438, 6670530439, 6670530440, 6670530441, 6670530442], "tags": {"power": "minor_line"}}]}